{"filename":"D:\\projects\\azure-cloud\\azure-cloud-main\\__azurite_db_blob_extent__.json","collections":[{"name":"$EXTENTS_COLLECTION$","data":[{"id":"16ede52b-c007-4300-9b93-a64074064cf2","locationId":"Default","path":"16ede52b-c007-4300-9b93-a64074064cf2","size":84770,"lastModifiedInMS":1701803602064,"meta":{"revision":15,"created":1701803602065,"version":0,"updated":1701815512259},"$loki":5,"LastModifyInMS":1701815512259},{"id":"15adbc3f-2c64-4e7c-9946-57d27896d469","locationId":"Default","path":"15adbc3f-2c64-4e7c-9946-57d27896d469","size":204513,"lastModifiedInMS":1701889344183,"meta":{"revision":43,"created":1701889344184,"version":0,"updated":1701896295674},"$loki":6,"LastModifyInMS":1701896295674}],"idIndex":[5,6],"binaryIndices":{"id":{"name":"id","dirty":false,"values":[1,0]}},"constraints":null,"uniqueNames":[],"transforms":{},"objType":"$EXTENTS_COLLECTION$","dirty":false,"cachedIndex":null,"cachedBinaryIndex":null,"cachedData":null,"adaptiveBinaryIndices":true,"transactional":false,"cloneObjects":false,"cloneMethod":"parse-stringify","asyncListeners":false,"disableMeta":false,"disableChangesApi":true,"disableDeltaChangesApi":true,"autoupdate":false,"serializableIndices":true,"disableFreeze":true,"ttl":null,"maxId":6,"DynamicViews":[],"events":{"insert":[],"update":[],"pre-insert":[],"pre-update":[],"close":[],"flushbuffer":[],"error":[],"delete":[null],"warning":[null]},"changes":[],"dirtyIds":[]}],"databaseVersion":1.5,"engineVersion":1.5,"autosave":true,"autosaveInterval":5000,"autosaveHandle":null,"throttledSaves":true,"options":{"persistenceMethod":"fs","autosave":true,"autosaveInterval":5000,"serializationMethod":"normal","destructureDelimiter":"$<\n"},"persistenceMethod":"fs","persistenceAdapter":null,"verbose":false,"events":{"init":[null],"loaded":[],"flushChanges":[],"close":[],"changes":[],"warning":[]},"ENV":"NODEJS"}